fastack_migrate/__init__.py
fastack_migrate/cli.py
fastack_migrate/globals.py
fastack_migrate/templates/fastack/README
fastack_migrate/templates/fastack/alembic.ini.mako
fastack_migrate/templates/fastack/env.py
fastack_migrate/templates/fastack/script.py.mako
fastack_migrate-0.4.2.dist-info/entry_points.txt
fastack_migrate-0.4.2.dist-info/LICENSE
fastack_migrate-0.4.2.dist-info/WHEEL
fastack_migrate-0.4.2.dist-info/METADATA
fastack_migrate-0.4.2.dist-info/RECORD
